Metadata-Version: 2.2
Name: kamusrejang_cli
Version: 0.2
Requires-Dist: requests
Requires-Dist: termcolor
Dynamic: requires-dist
